drb/topics/geojson/__init__.py
drb/topics/geojson/_version.py
drb/topics/geojson/cortex.yml
drb_topic_geojson-1.0.0.dist-info/METADATA
drb_topic_geojson-1.0.0.dist-info/WHEEL
drb_topic_geojson-1.0.0.dist-info/entry_points.txt
drb_topic_geojson-1.0.0.dist-info/top_level.txt
drb_topic_geojson-1.0.0.dist-info/RECORD
