Metadata-Version: 2.1
Name: drb-topic-geojson
Version: 1.0.0
Summary: DRB Python GeoJSON Topic
Home-page: https://gitlab.com/drb-python/topics/geojson
Author: GAEL Systems
Author-email: drb-python@gael.fr
License: LGPLv3
Project-URL: Source, https://gitlab.com/drb-python/topics/geojson
Classifier: Programming Language :: Python :: 3.8
Classifier: License :: OSI Approved :: GNU Lesser General Public License v3 (LGPLv3)
Requires-Python: >=3.8
Requires-Dist: drb-driver-json
